README.md
setup.py
command_line/__init__.py
command_line/__version__.py
command_line/core.py
command_line.egg-info/PKG-INFO
command_line.egg-info/SOURCES.txt
command_line.egg-info/dependency_links.txt
command_line.egg-info/entry_points.txt
command_line.egg-info/requires.txt
command_line.egg-info/top_level.txt